retrieve/__init__.py
retrieve/retrieve.py
retrieve-0.0.8.dist-info/LICENSE
retrieve-0.0.8.dist-info/METADATA
retrieve-0.0.8.dist-info/WHEEL
retrieve-0.0.8.dist-info/top_level.txt
retrieve-0.0.8.dist-info/RECORD
