Metadata-Version: 2.1
Name: retrieve
Version: 0.0.8
Summary: Retrieve pre-trained models and cache it locally
Home-page: https://github.com/amitness/retrieve
Author: Amit Chaudhary
Author-email: meamitkc@gmail.com
License: MIT
Platform: UNKNOWN
Classifier: Programming Language :: Python :: 3
Requires-Dist: requests
Requires-Dist: tqdm
